player1dev/__init__.py
player1dev/client.py
player1dev/server.py
player1dev/views/__init__.py
player1dev/views/creator_mode.py
player1dev/views/default.py
player1dev-1.0.10.dist-info/LICENSE
player1dev-1.0.10.dist-info/METADATA
player1dev-1.0.10.dist-info/WHEEL
player1dev-1.0.10.dist-info/top_level.txt
player1dev-1.0.10.dist-info/RECORD
