Metadata-Version: 2.1
Name: player1dev
Version: 1.0.10
Summary: A framework for perfectionists to build at light speed. Powered by Flet (Flutter) and FastAPI.
Author-email: Ophuscado <postbox@ophuscado.com>
License: Copyright (c) 2020-2023, Ophuscado LLC.
Project-URL: Author, https://ophuscado.com/?pypi=player1dev
Project-URL: Homepage, https://github.com/Ophuscado/py-player1dev
Keywords: framework,desktop,web,api,fastapi,flutter,flet
Classifier: License :: OSI Approved :: BSD License
Classifier: Programming Language :: Python
Classifier: Programming Language :: Python :: 3
Classifier: Programming Language :: Python :: 3.9
Classifier: Programming Language :: Python :: 3.10
Classifier: Programming Language :: Python :: 3.11
Requires-Python: >=3.9
License-File: LICENSE
Requires-Dist: fastapi
Requires-Dist: flet
Requires-Dist: jinja2
Requires-Dist: lxml
Requires-Dist: markdown
Requires-Dist: passlib
Requires-Dist: pymongo
Requires-Dist: python-dotenv
Requires-Dist: python-jwt
Requires-Dist: uvicorn
Requires-Dist: wheel
Provides-Extra: dev
Requires-Dist: black ; extra == 'dev'
Requires-Dist: ipdb ; extra == 'dev'
Requires-Dist: ipython ; extra == 'dev'
Requires-Dist: isort ; extra == 'dev'
Requires-Dist: pylint ; extra == 'dev'
Requires-Dist: twine ; extra == 'dev'
